imstegan/__init__.py
imstegan/__main__.py
imstegan/algo/DCT.py
imstegan/algo/LSB.py
imstegan/algo/LSBM.py
imstegan/algo/PVD.py
imstegan/algo/__init__.py
imstegan/algo/edge.py
imstegan/utils/__init__.py
imstegan/utils/conv2d.py
imstegan/utils/dct8.py
imstegan/utils/general.py
imstegan-0.0.2.dist-info/LICENSE
imstegan-0.0.2.dist-info/METADATA
imstegan-0.0.2.dist-info/WHEEL
imstegan-0.0.2.dist-info/top_level.txt
imstegan-0.0.2.dist-info/RECORD
